texplotlibx/__init__.py
texplotlibx/attribute.py
texplotlibx/cycle_list.py
texplotlibx/figure.py
texplotlibx/limits.py
texplotlibx/logmodes.py
texplotlibx/strutils.py
texplotlibx/util.py
texplotlibx/annotations/__init__.py
texplotlibx/annotations/annotation.py
texplotlibx/annotations/curve_label.py
texplotlibx/annotations/label.py
texplotlibx/annotations/legend.py
texplotlibx/annotations/ticklabel.py
texplotlibx/curve/__init__.py
texplotlibx/curve/curve.py
texplotlibx/curve/curve_data.py
texplotlibx/curve/mark.py
texplotlibx/curve/curve_generator/__init__.py
texplotlibx/curve/curve_generator/correlated_data.py
texplotlibx/curve/curve_generator/curve_generator.py
texplotlibx/curve/curve_generator/get_generator.py
texplotlibx/curve/curve_generator/lines.py
texplotlibx/curve/curve_generator/ybar.py
texplotlibx-1.1.2.dist-info/LICENSE
texplotlibx-1.1.2.dist-info/METADATA
texplotlibx-1.1.2.dist-info/WHEEL
texplotlibx-1.1.2.dist-info/top_level.txt
texplotlibx-1.1.2.dist-info/RECORD
