Metadata-Version: 2.1
Name: texplotlibx
Version: 1.1.2
Summary: A plot library for creating graphics using tikz/pgfplots
Home-page: https://gitlab.com/d_hir/texplotlib
Author: D Hir
Author-email: d_hir@outlook.com
Classifier: Programming Language :: Python :: 3
Classifier: License :: OSI Approved :: GNU General Public License v3 (GPLv3)
Classifier: Operating System :: POSIX
Classifier: Development Status :: 3 - Alpha
Requires-Python: >=3.6
License-File: LICENSE
